setup.py
bluefin/__init__.py
bluefin.egg-info/PKG-INFO
bluefin.egg-info/SOURCES.txt
bluefin.egg-info/dependency_links.txt
bluefin.egg-info/requires.txt
bluefin.egg-info/top_level.txt
bluefin/dataretrieval/__init__.py
bluefin/dataretrieval/clients.py
bluefin/dataretrieval/exceptions.py
bluefin/directmode/__init__.py
bluefin/directmode/clients.py
bluefin/directmode/exceptions.py