Metadata-Version: 1.1
Name: bluefin
Version: 1.2
Summary: A simple Bluefin Payment System API.
Home-page: https://github.com/duointeractive/python-bluefin/
Author: Gregory Taylor
Author-email: gtaylor@duointeractive.com
License: MIT
Platform: any
Classifier: Development Status :: 5 - Production/Stable
Classifier: Intended Audience :: Developers
Classifier: License :: OSI Approved :: MIT License
Classifier: Operating System :: OS Independent
Classifier: Programming Language :: Python
Classifier: Topic :: Software Development :: Libraries :: Python Modules
